tempest_horizon/__init__.py
tempest_horizon/config.py
tempest_horizon/plugin.py
tempest_horizon/tests/__init__.py
tempest_horizon/tests/scenario/__init__.py
tempest_horizon/tests/scenario/test_dashboard_basic_ops.py
tempest_horizon-1.1.0.dist-info/DESCRIPTION.rst
tempest_horizon-1.1.0.dist-info/METADATA
tempest_horizon-1.1.0.dist-info/RECORD
tempest_horizon-1.1.0.dist-info/WHEEL
tempest_horizon-1.1.0.dist-info/entry_points.txt
tempest_horizon-1.1.0.dist-info/metadata.json
tempest_horizon-1.1.0.dist-info/pbr.json
tempest_horizon-1.1.0.dist-info/top_level.txt
