Metadata-Version: 2.0
Name: tempest-horizon
Version: 1.1.0
Summary: Tempest Plugin for Horizon tests
Home-page: https://opendev.org/openstack/tempest-horizon
Author: OpenStack
Author-email: openstack-discuss@lists.openstack.org
License: UNKNOWN
Platform: UNKNOWN
Classifier: Environment :: OpenStack
Classifier: Intended Audience :: Information Technology
Classifier: Intended Audience :: System Administrators
Classifier: License :: OSI Approved :: Apache Software License
Classifier: Operating System :: POSIX :: Linux
Classifier: Programming Language :: Python
Classifier: Programming Language :: Python :: 3
Classifier: Programming Language :: Python :: 3.6
Classifier: Programming Language :: Python :: 3.7
Requires-Dist: oslo.config (>=4.6.0)
Requires-Dist: pbr (!=2.1.0,>=2.0.0)
Requires-Dist: tempest (>=17.1.0)
